finee/__init__.py
finee/cache.py
finee/cli.py
finee/confidence.py
finee/extractor.py
finee/merchants.py
finee/normalizer.py
finee/prompt.py
finee/regex_engine.py
finee/schema.py
finee/validator.py
finee/backends/__init__.py
finee/backends/base.py
finee/backends/llamacpp_backend.py
finee/backends/mlx_backend.py
finee/backends/transformers_backend.py
finee-1.0.3.dist-info/METADATA
finee-1.0.3.dist-info/WHEEL
finee-1.0.3.dist-info/entry_points.txt
finee-1.0.3.dist-info/licenses/LICENSE
finee-1.0.3.dist-info/RECORD
