Metadata-Version: 2.4
Name: finee
Version: 1.0.3
Summary: Extract structured financial entities from Indian banking messages
Project-URL: Homepage, https://github.com/Ranjit0034/llm-mail-trainer
Project-URL: Documentation, https://huggingface.co/Ranjit0034/finance-entity-extractor
Project-URL: Repository, https://github.com/Ranjit0034/llm-mail-trainer
Project-URL: Issues, https://github.com/Ranjit0034/llm-mail-trainer/issues
Author-email: Ranjit Behera <ranjit.behera@example.com>
License-Expression: MIT
License-File: LICENSE
Keywords: banking,entity-extraction,finance,india,llm,nlp,phi-3,upi
Classifier: Development Status :: 5 - Production/Stable
Classifier: Intended Audience :: Developers
Classifier: Intended Audience :: Financial and Insurance Industry
Classifier: License :: OSI Approved :: MIT License
Classifier: Operating System :: OS Independent
Classifier: Programming Language :: Python :: 3
Classifier: Programming Language :: Python :: 3.9
Classifier: Programming Language :: Python :: 3.10
Classifier: Programming Language :: Python :: 3.11
Classifier: Programming Language :: Python :: 3.12
Classifier: Topic :: Office/Business :: Financial
Classifier: Topic :: Scientific/Engineering :: Artificial Intelligence
Classifier: Topic :: Text Processing :: General
Requires-Python: >=3.9
Requires-Dist: json-repair>=0.28.0
Requires-Dist: python-dateutil>=2.8.0
Provides-Extra: all
Requires-Dist: accelerate>=0.25.0; extra == 'all'
Requires-Dist: llama-cpp-python>=0.2.0; extra == 'all'
Requires-Dist: mlx-lm>=0.19.0; extra == 'all'
Requires-Dist: torch>=2.0.0; extra == 'all'
Requires-Dist: transformers>=4.36.0; extra == 'all'
Provides-Extra: cpu
Requires-Dist: llama-cpp-python>=0.2.0; extra == 'cpu'
Provides-Extra: cuda
Requires-Dist: accelerate>=0.25.0; extra == 'cuda'
Requires-Dist: torch>=2.0.0; extra == 'cuda'
Requires-Dist: transformers>=4.36.0; extra == 'cuda'
Provides-Extra: dev
Requires-Dist: black>=23.0.0; extra == 'dev'
Requires-Dist: mypy>=1.0.0; extra == 'dev'
Requires-Dist: pytest-cov>=4.1.0; extra == 'dev'
Requires-Dist: pytest>=7.4.0; extra == 'dev'
Requires-Dist: ruff>=0.1.0; extra == 'dev'
Provides-Extra: docs
Requires-Dist: mkdocs-material>=9.0.0; extra == 'docs'
Requires-Dist: mkdocs>=1.5.0; extra == 'docs'
Provides-Extra: metal
Requires-Dist: mlx-lm>=0.19.0; extra == 'metal'
